csv2md/__init__.py
csv2md/__main__.py
csv2md/exceptions.py
csv2md/table.py
csv2md/test_table.py
csv2md/test_utils.py
csv2md/utils.py
csv2md-1.4.0.dist-info/LICENSE
csv2md-1.4.0.dist-info/METADATA
csv2md-1.4.0.dist-info/WHEEL
csv2md-1.4.0.dist-info/entry_points.txt
csv2md-1.4.0.dist-info/top_level.txt
csv2md-1.4.0.dist-info/RECORD
