Metadata-Version: 2.1
Name: csv2md
Version: 1.4.0
Summary: Command line tool for converting CSV files into Markdown tables.
Home-page: https://github.com/lzakharov/csv2md
Author: Lev Zakharov
Author-email: l.j.zakharov@gmail.com
License: MIT License
License-File: LICENSE
